LICENSE.txt
MANIFEST.in
README.md
requirements.txt
setup.cfg
setup.py
./LICENSE.txt
./cog.yaml
./requirements.txt
./blip/configs/bert_config.json
./blip/configs/caption_coco.yaml
./blip/configs/med_config.json
./blip/configs/nlvr.yaml
./blip/configs/nocaps.yaml
./blip/configs/pretrain.yaml
./blip/configs/retrieval_coco.yaml
./blip/configs/retrieval_flickr.yaml
./blip/configs/retrieval_msrvtt.yaml
./blip/configs/vqa.yaml
./blip_vit.egg-info/SOURCES.txt
./blip_vit.egg-info/dependency_links.txt
./blip_vit.egg-info/requires.txt
./blip_vit.egg-info/top_level.txt
./venv/lib/python3.8/site-packages/Pygments-2.12.0.dist-info/entry_points.txt
./venv/lib/python3.8/site-packages/Pygments-2.12.0.dist-info/top_level.txt
./venv/lib/python3.8/site-packages/SecretStorage-3.3.2.dist-info/top_level.txt
./venv/lib/python3.8/site-packages/bleach-5.0.0.dist-info/top_level.txt
./venv/lib/python3.8/site-packages/bleach/_vendor/vendor.txt
./venv/lib/python3.8/site-packages/bleach/_vendor/html5lib-1.1.dist-info/top_level.txt
./venv/lib/python3.8/site-packages/certifi-2022.6.15.dist-info/top_level.txt
./venv/lib/python3.8/site-packages/cffi-1.15.0.dist-info/entry_points.txt
./venv/lib/python3.8/site-packages/cffi-1.15.0.dist-info/top_level.txt
./venv/lib/python3.8/site-packages/charset_normalizer-2.0.12.dist-info/entry_points.txt
./venv/lib/python3.8/site-packages/charset_normalizer-2.0.12.dist-info/top_level.txt
./venv/lib/python3.8/site-packages/commonmark-0.9.1.dist-info/entry_points.txt
./venv/lib/python3.8/site-packages/commonmark-0.9.1.dist-info/top_level.txt
./venv/lib/python3.8/site-packages/cryptography-37.0.2.dist-info/top_level.txt
./venv/lib/python3.8/site-packages/docutils-0.18.1.dist-info/COPYING.txt
./venv/lib/python3.8/site-packages/docutils-0.18.1.dist-info/top_level.txt
./venv/lib/python3.8/site-packages/docutils/parsers/rst/include/README.txt
./venv/lib/python3.8/site-packages/docutils/parsers/rst/include/isoamsa.txt
./venv/lib/python3.8/site-packages/docutils/parsers/rst/include/isoamsb.txt
./venv/lib/python3.8/site-packages/docutils/parsers/rst/include/isoamsc.txt
./venv/lib/python3.8/site-packages/docutils/parsers/rst/include/isoamsn.txt
./venv/lib/python3.8/site-packages/docutils/parsers/rst/include/isoamso.txt
./venv/lib/python3.8/site-packages/docutils/parsers/rst/include/isoamsr.txt
./venv/lib/python3.8/site-packages/docutils/parsers/rst/include/isobox.txt
./venv/lib/python3.8/site-packages/docutils/parsers/rst/include/isocyr1.txt
./venv/lib/python3.8/site-packages/docutils/parsers/rst/include/isocyr2.txt
./venv/lib/python3.8/site-packages/docutils/parsers/rst/include/isodia.txt
./venv/lib/python3.8/site-packages/docutils/parsers/rst/include/isogrk1.txt
./venv/lib/python3.8/site-packages/docutils/parsers/rst/include/isogrk2.txt
./venv/lib/python3.8/site-packages/docutils/parsers/rst/include/isogrk3.txt
./venv/lib/python3.8/site-packages/docutils/parsers/rst/include/isogrk4-wide.txt
./venv/lib/python3.8/site-packages/docutils/parsers/rst/include/isogrk4.txt
./venv/lib/python3.8/site-packages/docutils/parsers/rst/include/isolat1.txt
./venv/lib/python3.8/site-packages/docutils/parsers/rst/include/isolat2.txt
./venv/lib/python3.8/site-packages/docutils/parsers/rst/include/isomfrk-wide.txt
./venv/lib/python3.8/site-packages/idna-3.3.dist-info/top_level.txt
./venv/lib/python3.8/site-packages/importlib_metadata-4.11.4.dist-info/top_level.txt
./venv/lib/python3.8/site-packages/keyring-23.6.0.dist-info/entry_points.txt
./venv/lib/python3.8/site-packages/keyring-23.6.0.dist-info/top_level.txt
./venv/lib/python3.8/site-packages/pip-22.1.2.dist-info/LICENSE.txt
./venv/lib/python3.8/site-packages/pip-22.1.2.dist-info/entry_points.txt
./venv/lib/python3.8/site-packages/pip-22.1.2.dist-info/top_level.txt
./venv/lib/python3.8/site-packages/pkginfo-1.8.3.dist-info/LICENSE.txt
./venv/lib/python3.8/site-packages/pkginfo-1.8.3.dist-info/entry_points.txt
./venv/lib/python3.8/site-packages/pkginfo-1.8.3.dist-info/top_level.txt
./venv/lib/python3.8/site-packages/pycparser-2.21.dist-info/top_level.txt
./venv/lib/python3.8/site-packages/readme_renderer-35.0.dist-info/top_level.txt
./venv/lib/python3.8/site-packages/requests-2.28.0.dist-info/top_level.txt
./venv/lib/python3.8/site-packages/requests_toolbelt-0.9.1.dist-info/top_level.txt
./venv/lib/python3.8/site-packages/rfc3986-2.0.0.dist-info/top_level.txt
./venv/lib/python3.8/site-packages/setuptools-62.3.4.dist-info/entry_points.txt
./venv/lib/python3.8/site-packages/setuptools-62.3.4.dist-info/top_level.txt
./venv/lib/python3.8/site-packages/six-1.16.0.dist-info/top_level.txt
./venv/lib/python3.8/site-packages/twine-4.0.1.dist-info/entry_points.txt
./venv/lib/python3.8/site-packages/twine-4.0.1.dist-info/top_level.txt
./venv/lib/python3.8/site-packages/urllib3-1.26.9.dist-info/LICENSE.txt
./venv/lib/python3.8/site-packages/urllib3-1.26.9.dist-info/top_level.txt
./venv/lib/python3.8/site-packages/webencodings-0.5.1.dist-info/metadata.json
./venv/lib/python3.8/site-packages/webencodings-0.5.1.dist-info/top_level.txt
./venv/lib/python3.8/site-packages/wheel-0.37.1.dist-info/LICENSE.txt
./venv/lib/python3.8/site-packages/wheel-0.37.1.dist-info/entry_points.txt
./venv/lib/python3.8/site-packages/wheel-0.37.1.dist-info/top_level.txt
./venv/lib/python3.8/site-packages/zipp-3.8.0.dist-info/top_level.txt
blip_vit.egg-info/PKG-INFO
blip_vit.egg-info/SOURCES.txt
blip_vit.egg-info/dependency_links.txt
blip_vit.egg-info/requires.txt
blip_vit.egg-info/top_level.txt