Metadata-Version: 2.1
Name: blip-vit
Version: 0.0.3
Summary: BLIP: Bootstrapping Language-Image Pre-training for Unified Vision-Language Understanding and Generation
Home-page: https://github.com/fernandoTB/BLIP
Download-URL: https://github.com/fernandoTB/BLIP/archive/refs/tags/0.0.3.tar.gz
Author: salesforce
Author-email: junnan.li@salesforce.com
Keywords: 0.0.3
License-File: LICENSE.txt
